markb/__init__.py
markb/_version.py
markb/markb.py
markb/test_markb.py
markb-0.2.6.data/scripts/markb
markb-0.2.6.dist-info/LICENSE.txt
markb-0.2.6.dist-info/METADATA
markb-0.2.6.dist-info/WHEEL
markb-0.2.6.dist-info/top_level.txt
markb-0.2.6.dist-info/RECORD
