Metadata-Version: 2.1
Name: markb
Version: 0.2.6
Summary: Render a markdown file and open it in a browser
Home-page: https://github.com/amireldor/markb
Author: Amir Eldor
Author-email: amir@eize.ninja
License: UNKNOWN
Platform: UNKNOWN
Classifier: Development Status :: 4 - Beta
Classifier: Environment :: Console
Classifier: Programming Language :: Python :: 3
Classifier: Topic :: Utilities
Classifier: License :: OSI Approved :: MIT License
Requires-Dist: markdown2 (==2.3.8)
